parebrick/drawer.py
parebrick/main.py
parebrick/characters/balanced.py
parebrick/characters/neighbours.py
parebrick/characters/unbalanced.py
parebrick/characters/which_chromosome.py
parebrick/clustering/clustering.py
parebrick/clustering/distance_matrices.py
parebrick/tree/neighbours_utils.py
parebrick/tree/tree_holder.py
parebrick/utils/decorators.py
parebrick/utils/data/converters.py
parebrick/utils/data/parsers.py
parebrick/utils/data/stats.py
parebrick/utils/data/unique_gene_filters.py
PaReBrick-0.5.7.dist-info/LICENSE
PaReBrick-0.5.7.dist-info/METADATA
PaReBrick-0.5.7.dist-info/WHEEL
PaReBrick-0.5.7.dist-info/entry_points.txt
PaReBrick-0.5.7.dist-info/top_level.txt
PaReBrick-0.5.7.dist-info/RECORD
