Metadata-Version: 2.1
Name: PaReBrick
Version: 0.5.7
Summary: A bioinf tool for finding genome rearrangements in bacterial genomes
Home-page: https://github.com/ctlab/parallel-rearrangements
Author: Alexey Zabelkin
Author-email: a.zabelkin@itmo.ru
Keywords: genome rearrangements,phylogenetic trees,non-convex characters,synteny blocks,phylogenetic tree,pattern consistency
Classifier: Topic :: Scientific/Engineering :: Bio-Informatics
Classifier: License :: OSI Approved :: MIT License
Classifier: Programming Language :: Python :: 3
Classifier: Programming Language :: Python :: 3.6
Classifier: Programming Language :: Python :: 3.7
Classifier: Programming Language :: Python :: 3.8
Classifier: Programming Language :: Python :: 3.9
Classifier: Programming Language :: Python :: 3 :: Only
Requires-Python: >=3.6, <3.9
License-File: LICENSE
Requires-Dist: PyQt5
Requires-Dist: ete3
Requires-Dist: scikit-learn
Requires-Dist: seaborn >=0.11.0
Requires-Dist: bg
